jprint/__init__.py
jprint/jprint.py
jprint-1.6.dist-info/METADATA
jprint-1.6.dist-info/WHEEL
jprint-1.6.dist-info/RECORD
