Metadata-Version: 2.1
Name: jprint
Version: 1.6
Summary: A simple JSON and python dictionary pretty printer
License: MIT
Author: John Furr
Author-email: gnulnx@gmail.com
Requires-Python: >=3.7,<4.0
Classifier: License :: OSI Approved :: MIT License
Classifier: Operating System :: OS Independent
Classifier: Programming Language :: Python :: 3
Classifier: Programming Language :: Python :: 3.7
Classifier: Programming Language :: Python :: 3.8
Classifier: Programming Language :: Python :: 3.9
Classifier: Programming Language :: Python :: 3.10
Classifier: Programming Language :: Python :: 3.11
Classifier: Programming Language :: Python :: 3
Requires-Dist: Pygments (==2.15.0)
Project-URL: Homepage, https://github.com/gnulnx/jprint
